{
  "episode": 10,
  "translations": {
    "субтитры": [
      {
        "id": 991852,
        "url": "https://smotretanime.ru/translations/embed/216473",
        "language": "english",
        "quality": "dvd",
        "author": "",
        "watchesCount": 0,
        "uploader": "NerV"
      },
      {
        "id": 1118022,
        "url": "https://smotretanime.ru/translations/embed/588259",
        "language": "english",
        "quality": "dvd",
        "author": "Zero-Raws",
        "watchesCount": 0,
        "uploader": "NerV"
      },
      {
        "id": 1118052,
        "url": "https://smotretanime.ru/translations/embed/588296",
        "language": "russian",
        "quality": "dvd",
        "author": "",
        "watchesCount": 8,
        "uploader": "NerV"
      },
      {
        "id": 1926431,
        "url": "http://vk.com/video_ext.php?oid=322059420&id=456240381&hash=2c315183cd3bf5a5",
        "language": "russian",
        "quality": "dvd",
        "author": "",
        "watchesCount": 1,
        "uploader": "Ази-Дахака"
      },
      {
        "id": 1926502,
        "url": "http://video.sibnet.ru/shell.php?videoid=3573036",
        "language": "russian",
        "quality": "dvd",
        "author": "",
        "watchesCount": 0,
        "uploader": "Ази-Дахака"
      }
    ],
    "оригинал": [
      {
        "id": 991876,
        "url": "https://smotretanime.ru/translations/embed/216496",
        "language": "original",
        "quality": "dvd",
        "author": "Zero-Raws",
        "watchesCount": 0,
        "uploader": "NerV"
      },
      {
        "id": 1118070,
        "url": "https://smotretanime.ru/translations/embed/588316",
        "language": "original",
        "quality": "dvd",
        "author": "Zero-Raws",
        "watchesCount": 0,
        "uploader": "NerV"
      },
      {
        "id": 1926396,
        "url": "http://vk.com/video_ext.php?oid=322059420&id=456240343&hash=7581128ccc2be3f9",
        "language": "original",
        "quality": "dvd",
        "author": "",
        "watchesCount": 0,
        "uploader": "Ази-Дахака"
      },
      {
        "id": 1926466,
        "url": "http://video.sibnet.ru/shell.php?videoid=3571740",
        "language": "original",
        "quality": "dvd",
        "author": "",
        "watchesCount": 0,
        "uploader": "Ази-Дахака"
      }
    ]
  }
}