{
  "episode": 6,
  "translations": {
    "озвучка": [
      {
        "id": 992520,
        "url": "https://smotretanime.ru/translations/embed/889544",
        "language": "russian",
        "quality": "tv",
        "author": "AnimeVost (Salplak)",
        "watchesCount": 2722,
        "uploader": "NerV"
      },
      {
        "id": 997409,
        "url": "http://video.sibnet.ru/shell.php?videoid=2417762",
        "language": "russian",
        "quality": "unknown",
        "author": "",
        "watchesCount": 1011,
        "uploader": ""
      },
      {
        "id": 1466767,
        "url": "http://video.sibnet.ru/shell.php?videoid=2730419",
        "language": "russian",
        "quality": "unknown",
        "author": "4Anime (Ket)",
        "watchesCount": 514,
        "uploader": "Selirion"
      }
    ],
    "субтитры": [
      {
        "id": 966021,
        "url": "https://smotretanime.ru/translations/embed/855518",
        "language": "russian",
        "quality": "unknown",
        "author": "SоvetRomantica",
        "watchesCount": 8,
        "uploader": "wooterland"
      },
      {
        "id": 966040,
        "url": "https://smotretanime.ru/translations/embed/855507",
        "language": "russian",
        "quality": "tv",
        "author": "SоvetRomantica",
        "watchesCount": 471,
        "uploader": "NerV"
      },
      {
        "id": 980984,
        "url": "http://video.sibnet.ru/shell.php?videoid=2354287",
        "language": "russian",
        "quality": "unknown",
        "author": "SovetRomanticа (Ararararagi & Sempre_Libera)",
        "watchesCount": 259,
        "uploader": ""
      },
      {
        "id": 1404749,
        "url": "http://smotretanime.ru/translations/embed/955786",
        "language": "russian",
        "quality": "bd",
        "author": "SоvetRomantica",
        "watchesCount": 1639,
        "uploader": "sekigano"
      },
      {
        "id": 1598657,
        "url": "http://sovetromantica.com/embed/episode_99_6-subtitles",
        "language": "russian",
        "quality": "tv",
        "author": "SоvetRomantica",
        "watchesCount": 484,
        "uploader": "NovaLiS"
      },
      {
        "id": 1631357,
        "url": "http://video.sibnet.ru/shell.php?videoid=2639917",
        "language": "russian",
        "quality": "bd",
        "author": "SovetRomanticа (Ararararagi & Sempre_Libera)",
        "watchesCount": 517,
        "uploader": "Probni"
      },
      {
        "id": 1723989,
        "url": "http://smotretanime.ru/translations/embed/994787",
        "language": "russian",
        "quality": "bd",
        "author": "miha4406",
        "watchesCount": 251,
        "uploader": "arnotino"
      }
    ]
  }
}