{
  "episode": 1,
  "translations": {
    "озвучка": [
      {
        "id": 865304,
        "url": "http://vk.com/video_ext.php?oid=-88246306&id=171398794&hash=8d11767c13eaa2f9",
        "language": "russian",
        "quality": "dvd",
        "author": "ATOM",
        "watchesCount": 1698,
        "uploader": "Limon Limonovich"
      },
      {
        "id": 1570819,
        "url": "http://smotretanime.ru/translations/embed/165283",
        "language": "russian",
        "quality": "dvd",
        "author": "ATOM",
        "watchesCount": 310,
        "uploader": "FriDayXIII"
      },
      {
        "id": 1692592,
        "url": "http://vk.com/video_ext.php?oid=-51712074&id=456239246&hash=372596c46ec77d5e",
        "language": "russian",
        "quality": "bd",
        "author": "Diaton",
        "watchesCount": 75,
        "uploader": "Lina Fair"
      },
      {
        "id": 1758394,
        "url": "http://ok.ru/videoembed/730186648137",
        "language": "russian",
        "quality": "bd",
        "author": "DJATOM",
        "watchesCount": 55,
        "uploader": "Probni"
      }
    ],
    "субтитры": [
      {
        "id": 1461973,
        "url": "http://smotretanime.ru/translations/embed/955070",
        "language": "russian",
        "quality": "bd",
        "author": "Kos the Duck & Rosetau",
        "watchesCount": 547,
        "uploader": "HoHondar"
      },
      {
        "id": 1758397,
        "url": "http://ok.ru/videoembed/730188417609",
        "language": "russian",
        "quality": "bd",
        "author": "Kos the Duck & Rosetau",
        "watchesCount": 37,
        "uploader": "Probni"
      },
      {
        "id": 1839749,
        "url": "http://video.sibnet.ru/shell.php?videoid=2932880",
        "language": "russian",
        "quality": "bd",
        "author": "Kos the Duck & Rosetau",
        "watchesCount": 88,
        "uploader": "Möbius"
      }
    ]
  }
}