{
  "episode": 14,
  "translations": {
    "озвучка": [
      {
        "id": 1021657,
        "url": "http://vk.com/video_ext.php?oid=-23081559&id=165844107&hash=dd2c997e1916c87d",
        "language": "russian",
        "quality": "tv",
        "author": "Е. Лурье",
        "watchesCount": 119,
        "uploader": "Sawansa"
      },
      {
        "id": 1697599,
        "url": "http://smotretanime.ru/translations/embed/865554",
        "language": "russian",
        "quality": "dvd",
        "author": "Е. Лурье",
        "watchesCount": 12,
        "uploader": "C_R_4_P"
      }
    ],
    "субтитры": [
      {
        "id": 1806515,
        "url": "http://smotretanime.ru/translations/embed/772057",
        "language": "russian",
        "quality": "dvd",
        "author": "",
        "watchesCount": 10,
        "uploader": "YuzuruNishimiya"
      }
    ],
    "оригинал": [
      {
        "id": 1806537,
        "url": "http://smotretanime.ru/translations/embed/1899430",
        "language": "original",
        "quality": "bd",
        "author": "LowPower-Raws",
        "watchesCount": 0,
        "uploader": "YuzuruNishimiya"
      }
    ]
  }
}