{
  "episode": 3,
  "translations": {
    "озвучка": [
      {
        "id": 682960,
        "url": "http://video.sibnet.ru/shell.php?videoid=1246617",
        "language": "russian",
        "quality": "unknown",
        "author": "AniLibria (Absurd & Eladiel)",
        "watchesCount": 159,
        "uploader": ""
      },
      {
        "id": 682973,
        "url": "http://video.sibnet.ru/shell.php?videoid=1246750",
        "language": "russian",
        "quality": "unknown",
        "author": "Zack_Fair",
        "watchesCount": 13,
        "uploader": ""
      },
      {
        "id": 870502,
        "url": "http://vk.com/video_ext.php?oid=-51405790&id=164559854&hash=c4ad26791fda9a4d",
        "language": "unknown",
        "quality": "unknown",
        "author": "AniLibria (Absurd & Eladiel)",
        "watchesCount": 1661,
        "uploader": "curacuza one"
      },
      {
        "id": 1009991,
        "url": "https://smotretanime.ru/translations/embed/244203",
        "language": "russian",
        "quality": "bd",
        "author": "AniLibria (Absurd & Eladiel)",
        "watchesCount": 1323,
        "uploader": "NerV"
      },
      {
        "id": 1010005,
        "url": "https://smotretanime.ru/translations/embed/244216",
        "language": "russian",
        "quality": "bd",
        "author": "Darmen",
        "watchesCount": 98,
        "uploader": "NerV"
      },
      {
        "id": 1010013,
        "url": "https://smotretanime.ru/translations/embed/244224",
        "language": "russian",
        "quality": "bd",
        "author": "Zack_Fair",
        "watchesCount": 90,
        "uploader": "NerV"
      },
      {
        "id": 1354525,
        "url": "http://vk.com/video_ext.php?oid=-23081559&id=171030635&hash=f5d406faab6602b5",
        "language": "russian",
        "quality": "tv",
        "author": "Zack_Fair",
        "watchesCount": 811,
        "uploader": "Kredon"
      }
    ],
    "субтитры": [
      {
        "id": 682947,
        "url": "http://video.sibnet.ru/shell.php?videoid=1246446",
        "language": "russian",
        "quality": "unknown",
        "author": "",
        "watchesCount": 190,
        "uploader": ""
      },
      {
        "id": 744142,
        "url": "http://vk.com/video_ext.php?oid=-67133214&id=168139014&hash=f8f3afba9abd1688",
        "language": "russian",
        "quality": "unknown",
        "author": "Dreamers Team",
        "watchesCount": 588,
        "uploader": ""
      },
      {
        "id": 1000929,
        "url": "https://smotretanime.ru/translations/embed/229867",
        "language": "russian",
        "quality": "bd",
        "author": "",
        "watchesCount": 512,
        "uploader": "NerV"
      },
      {
        "id": 1010032,
        "url": "https://smotretanime.ru/translations/embed/244244",
        "language": "russian",
        "quality": "bd",
        "author": "Dreamers Team",
        "watchesCount": 116,
        "uploader": "NerV"
      },
      {
        "id": 1032389,
        "url": "https://smotretanime.ru/translations/embed/288795",
        "language": "english",
        "quality": "bd",
        "author": "",
        "watchesCount": 5,
        "uploader": "NerV"
      },
      {
        "id": 1054923,
        "url": "https://smotretanime.ru/translations/embed/385793",
        "language": "russian",
        "quality": "bd",
        "author": "Amarillis & Looriental & anki 124 & junnes",
        "watchesCount": 147,
        "uploader": "NerV"
      },
      {
        "id": 1084202,
        "url": "https://smotretanime.ru/translations/embed/432713",
        "language": "english",
        "quality": "bd",
        "author": "ANE",
        "watchesCount": 6,
        "uploader": "NerV"
      }
    ],
    "оригинал": [
      {
        "id": 872708,
        "url": "http://vk.com/video_ext.php?oid=163464962&id=167778725&hash=5f0cb830fb1ff88c",
        "language": "unknown",
        "quality": "unknown",
        "author": "",
        "watchesCount": 3,
        "uploader": "kagerou"
      },
      {
        "id": 1000930,
        "url": "https://smotretanime.ru/translations/embed/229868",
        "language": "original",
        "quality": "bd",
        "author": "",
        "watchesCount": 6,
        "uploader": "NerV"
      },
      {
        "id": 1010049,
        "url": "https://smotretanime.ru/translations/embed/244259",
        "language": "original",
        "quality": "bd",
        "author": "Winter",
        "watchesCount": 0,
        "uploader": "NerV"
      },
      {
        "id": 1054936,
        "url": "https://smotretanime.ru/translations/embed/385808",
        "language": "original",
        "quality": "bd",
        "author": "ANE",
        "watchesCount": 0,
        "uploader": "NerV"
      }
    ]
  }
}