{
  "episode": 3,
  "translations": {
    "озвучка": [
      {
        "id": 1726863,
        "url": "http://smotretanime.ru/translations/embed/1805476",
        "language": "russian",
        "quality": "web",
        "author": "AnimeVost (Mensh)",
        "watchesCount": 1613,
        "uploader": "NerV"
      },
      {
        "id": 1726869,
        "url": "http://video.sibnet.ru/shell.php?videoid=3300869",
        "language": "russian",
        "quality": "web",
        "author": "AnimeVost (Mensh)",
        "watchesCount": 1303,
        "uploader": "sttany"
      },
      {
        "id": 1931589,
        "url": "http://vk.com/video_ext.php?oid=437725253&id=456239114&hash=96356dcf73f20ce0",
        "language": "russian",
        "quality": "web",
        "author": "AnimeVost (Mensh)",
        "watchesCount": 142,
        "uploader": "Uegien"
      }
    ]
  }
}