{
  "episode": 2,
  "translations": {
    "озвучка": [
      {
        "id": 1866226,
        "url": "http://video.sibnet.ru/shell.php?videoid=3497954",
        "language": "russian",
        "quality": "dvd",
        "author": "AniDUB (Macaron)",
        "watchesCount": 166,
        "uploader": "Probni"
      }
    ],
    "субтитры": [
      {
        "id": 553908,
        "url": "http://vk.com/video_ext.php?oid=188053847&id=166701796&hash=f8683f92931c1f55",
        "language": "russian",
        "quality": "unknown",
        "author": "kuro & Говорящий попугай",
        "watchesCount": 461,
        "uploader": ""
      },
      {
        "id": 924218,
        "url": "http://video.sibnet.ru/shell.php?videoid=1276766",
        "language": "russian",
        "quality": "unknown",
        "author": "kuro & Говорящий попугай",
        "watchesCount": 21,
        "uploader": ""
      },
      {
        "id": 1817066,
        "url": "http://vk.com/video_ext.php?oid=-64282268&id=456240369&hash=cb2bc6a37eb6d45b",
        "language": "russian",
        "quality": "dvd",
        "author": "kuro & Говорящий попугай",
        "watchesCount": 8,
        "uploader": "Probni"
      }
    ]
  }
}