{
  "episode": 1,
  "translations": {
    "озвучка": [
      {
        "id": 805299,
        "url": "http://vk.com/video_ext.php?oid=-87794159&id=171090288&hash=a6c5d6534c06b496",
        "language": "unknown",
        "quality": "unknown",
        "author": "AniMedia (Nazel & Freya)",
        "watchesCount": 3652,
        "uploader": "Юля Ангел"
      }
    ],
    "субтитры": [
      {
        "id": 1219940,
        "url": "http://video.sibnet.ru/shell.php?videoid=1646821",
        "language": "russian",
        "quality": "web",
        "author": "Наталия Ишова",
        "watchesCount": 250,
        "uploader": ""
      }
    ]
  }
}