{
  "episode": 2,
  "translations": {
    "озвучка": [
      {
        "id": 564911,
        "url": "http://vk.com/video_ext.php?oid=93219534&id=165791273&hash=1f0a37533812df96",
        "language": "russian",
        "quality": "unknown",
        "author": "JWA Project",
        "watchesCount": 1284,
        "uploader": ""
      },
      {
        "id": 730651,
        "url": "http://video.sibnet.ru/shell.php?videoid=409379",
        "language": "russian",
        "quality": "unknown",
        "author": "",
        "watchesCount": 62,
        "uploader": ""
      },
      {
        "id": 730653,
        "url": "http://vk.com/video_ext.php?oid=-24785917&id=162201519&hash=995a31063a6f8709",
        "language": "russian",
        "quality": "unknown",
        "author": "Suzaku",
        "watchesCount": 291,
        "uploader": ""
      },
      {
        "id": 811301,
        "url": "http://vk.com/video_ext.php?oid=133847534&id=168816186&hash=65acfa345be7df46",
        "language": "unknown",
        "quality": "unknown",
        "author": "SeM&Ko (MifSnaiper & Mirra)",
        "watchesCount": 280,
        "uploader": "SkywalterDBZ"
      },
      {
        "id": 1007894,
        "url": "https://smotretanime.ru/translations/embed/241222",
        "language": "russian",
        "quality": "bd",
        "author": "",
        "watchesCount": 878,
        "uploader": "NerV"
      },
      {
        "id": 1168980,
        "url": "https://smotretanime.ru/translations/embed/684825",
        "language": "russian",
        "quality": "tv",
        "author": "SeM&Ko (MifSnaiper & Mirra)",
        "watchesCount": 391,
        "uploader": "NerV"
      },
      {
        "id": 1263070,
        "url": "http://vk.com/video_ext.php?oid=-57991263&id=166385068&hash=3c75bdaf34f87603",
        "language": "russian",
        "quality": "tv",
        "author": "AniMedia (Zendos & Absurd & Eladiel)",
        "watchesCount": 4450,
        "uploader": "Ze6ypo"
      },
      {
        "id": 1410397,
        "url": "http://vk.com/video_ext.php?oid=-23081559&id=168569166&hash=6bf60e5d64dfefff",
        "language": "russian",
        "quality": "tv",
        "author": "Е. Лурье & Алекс Килька",
        "watchesCount": 64,
        "uploader": "VelfSan"
      },
      {
        "id": 1884074,
        "url": "http://ok.ru/videoembed/1557005339317",
        "language": "russian",
        "quality": "dvd",
        "author": "SeM&Ko (MifSnaiper & Mirra)",
        "watchesCount": 12,
        "uploader": "gzeb"
      }
    ],
    "субтитры": [
      {
        "id": 564909,
        "url": "http://video.sibnet.ru/shell.php?videoid=408908",
        "language": "russian",
        "quality": "unknown",
        "author": "Advantage (Asgar & sagitarius & zafhos)",
        "watchesCount": 218,
        "uploader": ""
      },
      {
        "id": 730652,
        "url": "http://vk.com/video_ext.php?oid=-24785917&id=162201518&hash=576ce9f5979734cf",
        "language": "russian",
        "quality": "unknown",
        "author": "",
        "watchesCount": 641,
        "uploader": ""
      },
      {
        "id": 1007977,
        "url": "https://smotretanime.ru/translations/embed/241309",
        "language": "russian",
        "quality": "bd",
        "author": "",
        "watchesCount": 843,
        "uploader": "NerV"
      },
      {
        "id": 1031810,
        "url": "https://smotretanime.ru/translations/embed/288151",
        "language": "english",
        "quality": "bd",
        "author": "",
        "watchesCount": 0,
        "uploader": "NerV"
      },
      {
        "id": 1196279,
        "url": "https://smotretanime.ru/translations/embed/720342",
        "language": "russian",
        "quality": "tv",
        "author": "",
        "watchesCount": 1,
        "uploader": "NerV"
      },
      {
        "id": 1247954,
        "url": "http://smotretanime.ru/translations/embed/871833",
        "language": "russian",
        "quality": "dvd",
        "author": "",
        "watchesCount": 0,
        "uploader": "NerV"
      },
      {
        "id": 1249606,
        "url": "http://smotretanime.ru/translations/embed/881985",
        "language": "russian",
        "quality": "bd",
        "author": "Coalgirls",
        "watchesCount": 241,
        "uploader": "NerV"
      },
      {
        "id": 1253566,
        "url": "http://smotretanime.ru/translations/embed/899758",
        "language": "english",
        "quality": "bd",
        "author": "",
        "watchesCount": 1,
        "uploader": "NerV"
      },
      {
        "id": 1253567,
        "url": "http://smotretanime.ru/translations/embed/899759",
        "language": "english",
        "quality": "bd",
        "author": "",
        "watchesCount": 4,
        "uploader": "NerV"
      }
    ],
    "оригинал": [
      {
        "id": 1008029,
        "url": "https://smotretanime.ru/translations/embed/241362",
        "language": "original",
        "quality": "bd",
        "author": "",
        "watchesCount": 0,
        "uploader": "NerV"
      },
      {
        "id": 1196278,
        "url": "https://smotretanime.ru/translations/embed/720341",
        "language": "original",
        "quality": "tv",
        "author": "",
        "watchesCount": 4,
        "uploader": "NerV"
      },
      {
        "id": 1249610,
        "url": "http://smotretanime.ru/translations/embed/882035",
        "language": "original",
        "quality": "bd",
        "author": "",
        "watchesCount": 0,
        "uploader": "NerV"
      }
    ]
  }
}