{
  "episode": 4,
  "translations": {
    "озвучка": [
      {
        "id": 705733,
        "url": "http://video.sibnet.ru/shell.php?videoid=571576",
        "language": "russian",
        "quality": "unknown",
        "author": "SHIZA Project (Viki)",
        "watchesCount": 2,
        "uploader": ""
      },
      {
        "id": 1093308,
        "url": "https://smotretanime.ru/translations/embed/447619",
        "language": "russian",
        "quality": "tv",
        "author": "SHIZA Project (Viki)",
        "watchesCount": 9,
        "uploader": "NerV"
      },
      {
        "id": 1364639,
        "url": "http://vk.com/video_ext.php?oid=-12323082&id=167641342&hash=416e6a956069b279",
        "language": "russian",
        "quality": "tv",
        "author": "SHIZA Project (Viki)",
        "watchesCount": 27,
        "uploader": "Kira157"
      }
    ],
    "субтитры": [
      {
        "id": 1868210,
        "url": "http://smotretanime.ru/translations/embed/599242",
        "language": "russian",
        "quality": "unknown",
        "author": "",
        "watchesCount": 2,
        "uploader": "Dale"
      }
    ]
  }
}