{
  "episode": 1,
  "translations": {
    "озвучка": [
      {
        "id": 1797829,
        "url": "http://smotretanime.ru/translations/embed/1891884",
        "language": "russian",
        "quality": "unknown",
        "author": "AniStar (Shoker)",
        "watchesCount": 646,
        "uploader": "Ruwasu"
      },
      {
        "id": 1797869,
        "url": "http://video.sibnet.ru/shell.php?videoid=3410717",
        "language": "russian",
        "quality": "tv",
        "author": "AniStar (Shoker)",
        "watchesCount": 326,
        "uploader": "sttany"
      },
      {
        "id": 1807421,
        "url": "http://smotretanime.ru/translations/embed/1903692",
        "language": "russian",
        "quality": "unknown",
        "author": "AniStar & VoiceWay (ArtLight & Owansei & Shoker & Kimamire & Sakura)",
        "watchesCount": 344,
        "uploader": "Гость"
      },
      {
        "id": 1807422,
        "url": "http://vk.com/video_ext.php?oid=-151306408&id=456239025&hash=d105d11ea039451f",
        "language": "russian",
        "quality": "unknown",
        "author": "AniStar & VoiceWay (ArtLight & Owansei & Shoker & Kimamire & Sakura)",
        "watchesCount": 1856,
        "uploader": "Гость"
      },
      {
        "id": 1807613,
        "url": "http://sovetromantica.com/embed/episode_584_1-dubbed",
        "language": "russian",
        "quality": "unknown",
        "author": "AniStar & VoiceWay (ArtLight & Owansei & Shoker & Kimamire & Sakura)",
        "watchesCount": 203,
        "uploader": "GooG2e"
      },
      {
        "id": 1814205,
        "url": "http://vk.com/video_ext.php?oid=-151973433&id=456239752&hash=b6fb8bd72d93b6e9",
        "language": "russian",
        "quality": "tv",
        "author": "StreamSound (Shane & BakaSenpai & Minaka & LemonLemonovich)",
        "watchesCount": 81,
        "uploader": "Shane SS"
      },
      {
        "id": 1814214,
        "url": "http://smotretanime.ru/translations/embed/1920967",
        "language": "russian",
        "quality": "tv",
        "author": "StreamSound (Shane & BakaSenpai & Minaka & LemonLemonovich)",
        "watchesCount": 7,
        "uploader": "Shane SS"
      },
      {
        "id": 1814229,
        "url": "http://video.sibnet.ru/shell.php?videoid=3425114",
        "language": "russian",
        "quality": "tv",
        "author": "StreamSound (Shane & BakaSenpai & Minaka & LemonLemonovich)",
        "watchesCount": 275,
        "uploader": "Shane SS"
      },
      {
        "id": 1826295,
        "url": "http://vk.com/video_ext.php?oid=-130387070&id=456239445&hash=a890a8b9cd987db5",
        "language": "russian",
        "quality": "tv",
        "author": "Flarrow Films (Lunar Arrow & Ron & Reina & Dreamy Sleep & Shira Senpai & AshVoice & AriannaFray & Cpt Drusha & Morvin & Nate)",
        "watchesCount": 367,
        "uploader": "Kurt_Solo"
      },
      {
        "id": 1854043,
        "url": "http://video.sibnet.ru/shell.php?videoid=3483657",
        "language": "russian",
        "quality": "web",
        "author": "AniDUB (Ancord & Jade)",
        "watchesCount": 307,
        "uploader": "Probni"
      },
      {
        "id": 1858311,
        "url": "http://vk.com/video_ext.php?oid=-89346355&id=456239265&hash=c10b44ff9b3afa27",
        "language": "russian",
        "quality": "tv",
        "author": "AniDUB (Ancord & Jade)",
        "watchesCount": 703,
        "uploader": "Ruwasu"
      },
      {
        "id": 1858312,
        "url": "http://smotretanime.ru/translations/embed/2022295",
        "language": "russian",
        "quality": "tv",
        "author": "AniDUB (Ancord & Jade)",
        "watchesCount": 336,
        "uploader": "Ruwasu"
      },
      {
        "id": 1865666,
        "url": "http://video.sibnet.ru/shell.php?videoid=3456044",
        "language": "russian",
        "quality": "web",
        "author": "Flarrow Films (Lunar Arrow & Ron & Reina & Dreamy Sleep & Shira Senpai & AshVoice & AriannaFray & Cpt Drusha & Morvin & Nate)",
        "watchesCount": 48,
        "uploader": "Probni"
      },
      {
        "id": 1873207,
        "url": "http://online.animedia.tv/embed/15865/1/1",
        "language": "russian",
        "quality": "tv",
        "author": "AniMedia (MezIdA & Soer)",
        "watchesCount": 9,
        "uploader": "Gintamen"
      },
      {
        "id": 1875973,
        "url": "http://vk.com/video_ext.php?oid=-125607934&id=456239017&hash=8e62dfee4219f26b",
        "language": "russian",
        "quality": "web",
        "author": "AniMaunt (Nokinal & Euler & leoneo & VieliS & Рейви & Lelik_time)",
        "watchesCount": 626,
        "uploader": "Nokinal"
      },
      {
        "id": 1896108,
        "url": "http://vk.com/video_ext.php?oid=421575736&id=456239258&hash=8a3e10974c2906fa",
        "language": "russian",
        "quality": "tv",
        "author": "AniMedia (MezIdA & Soer)",
        "watchesCount": 6,
        "uploader": "Ruwasu"
      },
      {
        "id": 1896122,
        "url": "http://smotretanime.ru/translations/embed/2232251",
        "language": "russian",
        "quality": "tv",
        "author": "AniMedia (MezIdA & Soer)",
        "watchesCount": 7,
        "uploader": "Ruwasu"
      },
      {
        "id": 1940438,
        "url": "http://vk.com/video_ext.php?oid=-39376197&id=456243253&hash=51498a6b764ed249",
        "language": "russian",
        "quality": "tv",
        "author": "KANSAI Studio",
        "watchesCount": 13,
        "uploader": "Welf_Krodz"
      }
    ],
    "субтитры": [
      {
        "id": 1798962,
        "url": "http://video.sibnet.ru/shell.php?videoid=3411773",
        "language": "english",
        "quality": "tv",
        "author": "",
        "watchesCount": 51,
        "uploader": "Lina Fair"
      },
      {
        "id": 1807492,
        "url": "http://smotretanime.ru/translations/embed/1893531",
        "language": "english",
        "quality": "unknown",
        "author": "HorribleSubs",
        "watchesCount": 48,
        "uploader": "Ohisama"
      },
      {
        "id": 1810819,
        "url": "http://smotretanime.ru/translations/embed/1915313",
        "language": "russian",
        "quality": "unknown",
        "author": "MedusaSub",
        "watchesCount": 271,
        "uploader": "Миюки Кавамура"
      },
      {
        "id": 1810827,
        "url": "http://vk.com/video_ext.php?oid=-158435497&id=456243985&hash=a65b832c220bbc47",
        "language": "russian",
        "quality": "unknown",
        "author": "MedusaSub",
        "watchesCount": 124,
        "uploader": "Миюки Кавамура"
      },
      {
        "id": 1811190,
        "url": "http://vk.com/video_ext.php?oid=90049435&id=456239132&hash=d4fdadc8fd2dbabe",
        "language": "russian",
        "quality": "web",
        "author": "Doggy Subs (FriendyS)",
        "watchesCount": 220,
        "uploader": "FriendyS"
      },
      {
        "id": 1832386,
        "url": "http://video.sibnet.ru/shell.php?videoid=3454260",
        "language": "russian",
        "quality": "unknown",
        "author": "MedusaSub",
        "watchesCount": 54,
        "uploader": "Ohisama"
      },
      {
        "id": 1833515,
        "url": "http://sovetromantica.com/embed/episode_584_1-subtitles",
        "language": "russian",
        "quality": "tv",
        "author": "SovetRomantica",
        "watchesCount": 299,
        "uploader": "GooG2e"
      },
      {
        "id": 1833716,
        "url": "http://video.sibnet.ru/shell.php?videoid=3456027",
        "language": "russian",
        "quality": "tv",
        "author": "SovetRomanticа",
        "watchesCount": 33,
        "uploader": "Ohisama"
      }
    ],
    "оригинал": [
      {
        "id": 1807491,
        "url": "http://smotretanime.ru/translations/embed/1893532",
        "language": "original",
        "quality": "unknown",
        "author": "HorribleSubs",
        "watchesCount": 68,
        "uploader": "Ohisama"
      },
      {
        "id": 1814745,
        "url": "http://video.sibnet.ru/shell.php?videoid=3425406",
        "language": "original",
        "quality": "web",
        "author": "HorribleSubs",
        "watchesCount": 1,
        "uploader": "Probni"
      }
    ]
  }
}