{
  "episode": 4,
  "translations": {
    "озвучка": [
      {
        "id": 1666144,
        "url": "http://video.sibnet.ru/shell.php?videoid=3218869",
        "language": "russian",
        "quality": "tv",
        "author": "AnimeVost (LeConik)",
        "watchesCount": 174,
        "uploader": "sttany"
      },
      {
        "id": 1666145,
        "url": "http://video.sibnet.ru/shell.php?videoid=3218871",
        "language": "russian",
        "quality": "tv",
        "author": "AniStar (Shoker)",
        "watchesCount": 107,
        "uploader": "sttany"
      },
      {
        "id": 1677728,
        "url": "http://smotretanime.ru/translations/embed/1682683",
        "language": "russian",
        "quality": "tv",
        "author": "AniPlay (ArtLight)",
        "watchesCount": 3,
        "uploader": "Ger4og"
      },
      {
        "id": 1677731,
        "url": "http://smotretanime.ru/translations/embed/1680216",
        "language": "russian",
        "quality": "tv",
        "author": "AnimeVost (LeConik)",
        "watchesCount": 103,
        "uploader": "Ger4og"
      },
      {
        "id": 1677734,
        "url": "http://smotretanime.ru/translations/embed/1680110",
        "language": "russian",
        "quality": "tv",
        "author": "AniStar (Shoker)",
        "watchesCount": 48,
        "uploader": "Ger4og"
      },
      {
        "id": 1677735,
        "url": "http://smotretanime.ru/translations/embed/1681844",
        "language": "russian",
        "quality": "tv",
        "author": "AniMaunt (Berofu)",
        "watchesCount": 136,
        "uploader": "Ger4og"
      }
    ],
    "субтитры": [
      {
        "id": 1666116,
        "url": "http://vk.com/video_ext.php?oid=-158435497&id=456240511&hash=66d1db6bd16dc51b",
        "language": "russian",
        "quality": "tv",
        "author": "MedusaSub",
        "watchesCount": 133,
        "uploader": "Юлий Хундрий"
      },
      {
        "id": 1668606,
        "url": "http://vk.com/video_ext.php?oid=-103382245&id=456239028&hash=eb741f57be225c65",
        "language": "russian",
        "quality": "tv",
        "author": "World Tailed",
        "watchesCount": 45,
        "uploader": "Гость"
      },
      {
        "id": 1677724,
        "url": "http://smotretanime.ru/translations/embed/1680339",
        "language": "russian",
        "quality": "tv",
        "author": "MedusaSub",
        "watchesCount": 68,
        "uploader": "Ger4og"
      },
      {
        "id": 1686993,
        "url": "http://video.sibnet.ru/shell.php?videoid=3248795",
        "language": "russian",
        "quality": "tv",
        "author": "YakuSub Studio (Nika_Elrik & Nagi)",
        "watchesCount": 35,
        "uploader": "Probni"
      },
      {
        "id": 1686994,
        "url": "http://smotretanime.ru/translations/embed/1708194",
        "language": "russian",
        "quality": "tv",
        "author": "Kasandra & sys3x",
        "watchesCount": 10,
        "uploader": "Probni"
      },
      {
        "id": 1687001,
        "url": "http://smotretanime.ru/translations/embed/1727198",
        "language": "russian",
        "quality": "tv",
        "author": "Nika_Elrik & Nagi",
        "watchesCount": 1,
        "uploader": "NerV"
      },
      {
        "id": 1699026,
        "url": "http://smotretanime.ru/translations/embed/1751616",
        "language": "russian",
        "quality": "tv",
        "author": "Nika_Elrik & Nagi",
        "watchesCount": 10,
        "uploader": "NerV"
      },
      {
        "id": 1705402,
        "url": "http://smotretanime.ru/translations/embed/1772095",
        "language": "russian",
        "quality": "tv",
        "author": "Kasandra & sys3x",
        "watchesCount": 0,
        "uploader": "NerV"
      },
      {
        "id": 1706629,
        "url": "http://smotretanime.ru/translations/embed/1772623",
        "language": "russian",
        "quality": "tv",
        "author": "Kasandra & sys3x",
        "watchesCount": 22,
        "uploader": "NerV"
      }
    ]
  }
}