{
  "episode": 6,
  "translations": {
    "озвучка": [
      {
        "id": 889658,
        "url": "http://vk.com/video_ext.php?oid=-74469996&id=170052465&hash=befbf01200948471",
        "language": "unknown",
        "quality": "unknown",
        "author": "Tinda",
        "watchesCount": 45,
        "uploader": "Ca.-Sig."
      },
      {
        "id": 1848569,
        "url": "http://video.sibnet.ru/shell.php?videoid=2906522",
        "language": "russian",
        "quality": "tv",
        "author": "SakuraNight (Tinda) (+ субтитры)",
        "watchesCount": 4,
        "uploader": "YJOS"
      }
    ],
    "субтитры": [
      {
        "id": 1282822,
        "url": "http://smotretanime.ru/translations/embed/542537",
        "language": "russian",
        "quality": "tv",
        "author": "",
        "watchesCount": 0,
        "uploader": "deleted account"
      },
      {
        "id": 1282832,
        "url": "http://vk.com/video_ext.php?oid=-37074141&id=168973947&hash=d849fce766db851e",
        "language": "russian",
        "quality": "tv",
        "author": "",
        "watchesCount": 38,
        "uploader": "deleted account"
      }
    ],
    "оригинал": [
      {
        "id": 1906901,
        "url": "http://vk.com/video_ext.php?oid=223485272&id=456239246&hash=58815d09df3ebf0e",
        "language": "original",
        "quality": "bd",
        "author": "",
        "watchesCount": 0,
        "uploader": "keyakizakka"
      }
    ]
  }
}