{
  "episode": 154,
  "translations": {
    "озвучка": [
      {
        "id": 533776,
        "url": "http://video.sibnet.ru/shell.php?videoid=641227",
        "language": "russian",
        "quality": "unknown",
        "author": "AniDUB (Ancord) (154-155)",
        "watchesCount": 828,
        "uploader": ""
      },
      {
        "id": 728987,
        "url": "http://vk.com/video_ext.php?oid=-38118063&id=162714791&hash=22f94f408b83e44b",
        "language": "russian",
        "quality": "unknown",
        "author": "AniDUB (Ancord) (154-155)",
        "watchesCount": 3590,
        "uploader": ""
      },
      {
        "id": 807043,
        "url": "http://vk.com/video_ext.php?oid=-31758767&id=162229417&hash=8fd2861d5b0bbe5f",
        "language": "unknown",
        "quality": "unknown",
        "author": "SHIZA Project (NIKITOS) (154-155)",
        "watchesCount": 236,
        "uploader": "SkywalterDBZ"
      },
      {
        "id": 1079084,
        "url": "https://smotretanime.ru/translations/embed/426618",
        "language": "russian",
        "quality": "tv",
        "author": "AnimeVost",
        "watchesCount": 160,
        "uploader": "NerV"
      },
      {
        "id": 1217100,
        "url": "http://vk.com/video_ext.php?oid=-37144938&id=163260808&hash=4f151c146e460188",
        "language": "russian",
        "quality": "tv",
        "author": "2x2 (154-155)",
        "watchesCount": 6,
        "uploader": "baksIII"
      },
      {
        "id": 1218207,
        "url": "http://vk.com/video_ext.php?oid=-24187629&id=163377474&hash=813ad5a37acd6d47",
        "language": "russian",
        "quality": "tv",
        "author": "2x2 (154-155)",
        "watchesCount": 2180,
        "uploader": "baksIII"
      },
      {
        "id": 1342221,
        "url": "http://smotretanime.ru/translations/embed/1062445",
        "language": "russian",
        "quality": "tv",
        "author": "",
        "watchesCount": 1,
        "uploader": "NerV"
      },
      {
        "id": 1342499,
        "url": "http://smotretanime.ru/translations/embed/957453",
        "language": "russian",
        "quality": "tv",
        "author": "",
        "watchesCount": 712,
        "uploader": "NerV"
      },
      {
        "id": 1371227,
        "url": "http://video.sibnet.ru/shell.php?videoid=1498587",
        "language": "russian",
        "quality": "unknown",
        "author": "SHIZA Project (NIKITOS)",
        "watchesCount": 299,
        "uploader": ""
      },
      {
        "id": 1960977,
        "url": "http://video.sibnet.ru/shell.php?videoid=3031356",
        "language": "russian",
        "quality": "tv",
        "author": "2x2",
        "watchesCount": 4,
        "uploader": "Asdi1"
      }
    ],
    "субтитры": [
      {
        "id": 655098,
        "url": "http://video.sibnet.ru/shell.php?videoid=417501",
        "language": "russian",
        "quality": "unknown",
        "author": "",
        "watchesCount": 17,
        "uploader": ""
      },
      {
        "id": 888253,
        "url": "http://vk.com/video_ext.php?oid=-5058030&id=148404901&hash=df01b57ac8369425",
        "language": "unknown",
        "quality": "unknown",
        "author": "",
        "watchesCount": 170,
        "uploader": "Tenno Haruka"
      },
      {
        "id": 1084938,
        "url": "https://smotretanime.ru/translations/embed/433741",
        "language": "english",
        "quality": "tv",
        "author": "HorribleSubs",
        "watchesCount": 17,
        "uploader": "NerV"
      },
      {
        "id": 1206867,
        "url": "https://smotretanime.ru/translations/embed/734081",
        "language": "russian",
        "quality": "tv",
        "author": "",
        "watchesCount": 551,
        "uploader": "NerV"
      },
      {
        "id": 1207588,
        "url": "https://smotretanime.ru/translations/embed/734983",
        "language": "russian",
        "quality": "tv",
        "author": "Кицунэ & Sirius_kh & X_beast & Hollow (154-155)",
        "watchesCount": 289,
        "uploader": "NerV"
      },
      {
        "id": 1275684,
        "url": "http://vk.com/video_ext.php?oid=-79746927&id=170280247&hash=72a51d05f721c263",
        "language": "russian",
        "quality": "tv",
        "author": "",
        "watchesCount": 388,
        "uploader": "plmlv"
      },
      {
        "id": 1373396,
        "url": "http://video.sibnet.ru/shell.php?videoid=1929435",
        "language": "russian",
        "quality": "unknown",
        "author": "",
        "watchesCount": 73,
        "uploader": ""
      },
      {
        "id": 1903913,
        "url": "http://www.myvi.top/embed/ddtcoc8icrdrpgxjocn88c1cwc",
        "language": "russian",
        "quality": "tv",
        "author": "Firegorn Team",
        "watchesCount": 25,
        "uploader": "Iwazaru"
      },
      {
        "id": 1910642,
        "url": "http://www.myvi.top/embed/8d8dfpc3qqawzb5toohxi1613y",
        "language": "russian",
        "quality": "tv",
        "author": "",
        "watchesCount": 40,
        "uploader": "Iwazaru"
      }
    ],
    "оригинал": [
      {
        "id": 1084937,
        "url": "https://smotretanime.ru/translations/embed/433740",
        "language": "original",
        "quality": "tv",
        "author": "HorribleSubs",
        "watchesCount": 3,
        "uploader": "NerV"
      }
    ]
  }
}