{
  "episode": 94,
  "translations": {
    "озвучка": [
      {
        "id": 1660988,
        "url": "http://youtube.com/embed/a3E5QT8o90Y",
        "language": "english",
        "quality": "unknown",
        "author": "",
        "watchesCount": 0,
        "uploader": "mak_sim"
      },
      {
        "id": 1661638,
        "url": "http://youtube.com/embed/0O_UuSu7YJg",
        "language": "russian",
        "quality": "tv",
        "author": "",
        "watchesCount": 0,
        "uploader": "Mono_Mishka"
      }
    ]
  }
}