{
  "episode": 68,
  "translations": {
    "озвучка": [
      {
        "id": 854631,
        "url": "http://vk.com/video_ext.php?oid=-34215076&id=171305939&hash=8399dc166088527a",
        "language": "unknown",
        "quality": "unknown",
        "author": "Sintop",
        "watchesCount": 73,
        "uploader": "sttany"
      },
      {
        "id": 855075,
        "url": "http://vk.com/video_ext.php?oid=-60200498&id=171461132&hash=1acd3ff7ba40bd1c",
        "language": "unknown",
        "quality": "unknown",
        "author": "Zendos & Eladiel",
        "watchesCount": 665,
        "uploader": "Kendo"
      },
      {
        "id": 858262,
        "url": "http://vk.com/video_ext.php?oid=-37468416&id=171462149&hash=36f2c4d991b9d717",
        "language": "unknown",
        "quality": "unknown",
        "author": "AniLibria (Lupin & Metacarmex & Aemi)",
        "watchesCount": 761,
        "uploader": "SineD_AL"
      },
      {
        "id": 923079,
        "url": "https://smotretanime.ru/translations/embed/847305",
        "language": "russian",
        "quality": "tv",
        "author": "AnimeVost",
        "watchesCount": 120,
        "uploader": "NerV"
      },
      {
        "id": 923781,
        "url": "http://video.sibnet.ru/shell.php?videoid=2038641",
        "language": "unknown",
        "quality": "unknown",
        "author": "Anything Group (Dajana & Sad_Kit)",
        "watchesCount": 24,
        "uploader": "Anything_Group"
      },
      {
        "id": 1120654,
        "url": "http://vk.com/video_ext.php?oid=-64461822&id=171230710&hash=fc5aeaefce5589f4",
        "language": "russian",
        "quality": "tv",
        "author": "ArtLight",
        "watchesCount": 152,
        "uploader": "ArtLight"
      },
      {
        "id": 1435049,
        "url": "http://video.sibnet.ru/shell.php?videoid=1931813",
        "language": "russian",
        "quality": "tv",
        "author": "AniDUB (Ancord)",
        "watchesCount": 5,
        "uploader": "NovaLiS"
      },
      {
        "id": 1435415,
        "url": "http://smotretanime.ru/translations/embed/443405",
        "language": "russian",
        "quality": "tv",
        "author": "AniLibria (Lupin & Metacarmex & Aemi)",
        "watchesCount": 112,
        "uploader": "baksIII"
      },
      {
        "id": 1438722,
        "url": "http://vk.com/video_ext.php?oid=-12323082&id=171722573&hash=af64c5b4713c325a",
        "language": "russian",
        "quality": "tv",
        "author": "SHIZA Project (Snowly & Oni)",
        "watchesCount": 157,
        "uploader": "Kira157"
      },
      {
        "id": 1439367,
        "url": "http://video.sibnet.ru/shell.php?videoid=1854452",
        "language": "russian",
        "quality": "tv",
        "author": "AniDUB (Ancord)",
        "watchesCount": 1500,
        "uploader": "NovaLiS"
      },
      {
        "id": 1662502,
        "url": "http://video.sibnet.ru/shell.php?videoid=2680944",
        "language": "russian",
        "quality": "tv",
        "author": "Anything Group (Dajana & Sad_Kit)",
        "watchesCount": 58,
        "uploader": "Iwazaru"
      },
      {
        "id": 1662614,
        "url": "http://video.sibnet.ru/shell.php?videoid=2681217",
        "language": "russian",
        "quality": "tv",
        "author": "Zendos & Eladiel",
        "watchesCount": 88,
        "uploader": "Iwazaru"
      },
      {
        "id": 1766027,
        "url": "http://ok.ru/videoembed/605050636852",
        "language": "russian",
        "quality": "tv",
        "author": "SHIZA Project (Snowly & Oni)",
        "watchesCount": 62,
        "uploader": "Iwazaru"
      },
      {
        "id": 1766137,
        "url": "http://videoapi.my.mail.ru/videos/embed/mail/animedub.ru/6/799.html",
        "language": "russian",
        "quality": "tv",
        "author": "Anything Group (Dajana & Sad_Kit)",
        "watchesCount": 31,
        "uploader": "Iwazaru"
      },
      {
        "id": 1796068,
        "url": "http://ok.ru/videoembed/37522115228",
        "language": "russian",
        "quality": "tv",
        "author": "AniDUB (Ancord)",
        "watchesCount": 100,
        "uploader": "Iwazaru"
      },
      {
        "id": 1816648,
        "url": "http://video.sibnet.ru/shell.php?videoid=3093714",
        "language": "russian",
        "quality": "tv",
        "author": "Get Smart Group (Persona99)",
        "watchesCount": 7,
        "uploader": "Юлия Калимулина"
      },
      {
        "id": 1958224,
        "url": "http://smotretanime.ru/translations/embed/1073313",
        "language": "russian",
        "quality": "bd",
        "author": "Anything Group (Dajana & Sad_Kit)",
        "watchesCount": 1,
        "uploader": "NECRORISE"
      }
    ],
    "субтитры": [
      {
        "id": 854707,
        "url": "http://vk.com/video_ext.php?oid=-75406714&id=171334124&hash=f7942a31e40c52f9",
        "language": "unknown",
        "quality": "unknown",
        "author": "ORA-ORA Project",
        "watchesCount": 273,
        "uploader": "Ryhiy"
      },
      {
        "id": 1086084,
        "url": "https://smotretanime.ru/translations/embed/435272",
        "language": "russian",
        "quality": "tv",
        "author": "Jenia aka Zub & Мария Гостюхина & Advokat",
        "watchesCount": 246,
        "uploader": "NerV"
      },
      {
        "id": 1177457,
        "url": "http://vk.com/video_ext.php?oid=246007966&id=171130088&hash=1b37bd1be66d9669",
        "language": "russian",
        "quality": "tv",
        "author": "",
        "watchesCount": 162,
        "uploader": "Gvendalin"
      },
      {
        "id": 1529269,
        "url": "http://video.sibnet.ru/shell.php?videoid=2679893",
        "language": "russian",
        "quality": "tv",
        "author": "Risens Team",
        "watchesCount": 169,
        "uploader": "Nii_chan"
      },
      {
        "id": 1807763,
        "url": "http://smotretanime.ru/translations/embed/1476066",
        "language": "russian",
        "quality": "bd",
        "author": "Fratelli & Antravoco",
        "watchesCount": 106,
        "uploader": "NovaLiS"
      }
    ],
    "оригинал": [
      {
        "id": 1086085,
        "url": "https://smotretanime.ru/translations/embed/435274",
        "language": "original",
        "quality": "tv",
        "author": "HorribleSubs",
        "watchesCount": 8,
        "uploader": "NerV"
      }
    ]
  }
}