{
  "episode": 11,
  "translations": {
    "озвучка": [
      {
        "id": 754707,
        "url": "http://vk.com/video_ext.php?oid=27644186&id=169077347&hash=7876978615cc679c",
        "language": "russian",
        "quality": "unknown",
        "author": "Persona99",
        "watchesCount": 10,
        "uploader": ""
      },
      {
        "id": 1145988,
        "url": "https://smotretanime.ru/translations/embed/649972",
        "language": "russian",
        "quality": "tv",
        "author": "Persona99",
        "watchesCount": 1,
        "uploader": "NerV"
      },
      {
        "id": 1815824,
        "url": "http://video.sibnet.ru/shell.php?videoid=2714932",
        "language": "russian",
        "quality": "dvd",
        "author": "Get Smart Group (Persona99)",
        "watchesCount": 2,
        "uploader": "Юлия Калимулина"
      }
    ]
  }
}