{
  "episode": 13,
  "translations": {
    "субтитры": [
      {
        "id": 1312955,
        "url": "http://youtube.com/embed/FtgHh0MugmU",
        "language": "english",
        "quality": "tv",
        "author": "",
        "watchesCount": 42,
        "uploader": "mak_sim"
      },
      {
        "id": 1863432,
        "url": "http://www.myvi.top/embed/j6fh55aphfuruy1biiix8cwm6a",
        "language": "russian",
        "quality": "dvd",
        "author": "Скай",
        "watchesCount": 4,
        "uploader": "Dale"
      }
    ]
  }
}